litecrypt/__init__.py
litecrypt/__main__.py
litecrypt/core/__init__.py
litecrypt/core/_base.py
litecrypt/core/crypt.py
litecrypt/core/datacrypt.py
litecrypt/core/filecrypt.py
litecrypt/core/helpers/__init__.py
litecrypt/core/helpers/funcs.py
litecrypt/core/safepack/__init__.py
litecrypt/core/safepack/gui.py
litecrypt/core/safepack/replicas.py
litecrypt/mapper/__init__.py
litecrypt/mapper/_consts.py
litecrypt/mapper/_definitions.py
litecrypt/mapper/_engines.py
litecrypt/mapper/_extras.py
litecrypt/mapper/_models.py
litecrypt/mapper/_types.py
litecrypt/mapper/database.py
litecrypt/py.typed
litecrypt/utils/__init__.py
litecrypt/utils/consts/__init__.py
litecrypt/utils/consts/main.py
litecrypt/utils/exceptions/__init__.py
litecrypt/utils/exceptions/dynamic.py
litecrypt/utils/exceptions/fixed.py
litecrypt-0.2.7.dist-info/LICENSE
litecrypt-0.2.7.dist-info/METADATA
litecrypt-0.2.7.dist-info/WHEEL
litecrypt-0.2.7.dist-info/RECORD
