Metadata-Version: 2.1
Name: litecrypt
Version: 0.2.7
Summary: Simplifying encryption
License: MIT
Author: Ashref Gwader
Author-email: AshrefGw@proton.me
Requires-Python: >=3.8,<4.0
Classifier: Development Status :: 5 - Production/Stable
Classifier: Intended Audience :: Developers
Classifier: License :: OSI Approved :: MIT License
Classifier: Operating System :: OS Independent
Classifier: Programming Language :: Python
Classifier: Programming Language :: Python :: 3
Classifier: Programming Language :: Python :: 3.8
Classifier: Programming Language :: Python :: 3.9
Classifier: Programming Language :: Python :: 3.10
Classifier: Programming Language :: Python :: 3.11
Classifier: Programming Language :: Python :: 3.12
Classifier: Typing :: Typed
Requires-Dist: SQLAlchemy (>=1.4.41,<2.0.0)
Requires-Dist: bcrypt (>=4.0.1,<5.0.0)
Requires-Dist: cryptography (>=40.0.2,<41.0.0)
Requires-Dist: qrcode (>=7.4.2,<8.0.0)
Requires-Dist: ttkbootstrap (>=1.10.1,<2.0.0)
